omniblack/cli/__init__.py
omniblack/cli/subcommands.py
omniblack.cli-0.0.2.dist-info/LICENSE.txt
omniblack.cli-0.0.2.dist-info/METADATA
omniblack.cli-0.0.2.dist-info/WHEEL
omniblack.cli-0.0.2.dist-info/top_level.txt
omniblack.cli-0.0.2.dist-info/RECORD
