Metadata-Version: 2.1
Name: omniblack.cli
Version: 0.0.2
Author-email: Terry Patterson <Terryp@wegrok.net>
License: 
Project-URL: Homepage, https://gitlab.com/terryp/terry/-/tree/next/lib/cli
Project-URL: Repository, https://gitlab.com/terryp/terry.git
License-File: LICENSE.txt
Requires-Dist: omniblack.entry
